hellowworlde/__init__.py
hellowworlde-0.1.dist-info/METADATA
hellowworlde-0.1.dist-info/WHEEL
hellowworlde-0.1.dist-info/top_level.txt
hellowworlde-0.1.dist-info/RECORD
