Metadata-Version: 2.1
Name: hellowworlde
Version: 0.1
Summary: Hellow Worlde
Home-page: UNKNOWN
Author: agung
Author-email: agung.96tm@gmail.com
License: MIT
Platform: UNKNOWN
